hubitat_maker_api_client/__init__.py
hubitat_maker_api_client/api_client.py
hubitat_maker_api_client/caching_client.py
hubitat_maker_api_client/capabilities.py
hubitat_maker_api_client/client.py
hubitat_maker_api_client/constants.py
hubitat_maker_api_client/device_cache.py
hubitat_maker_api_client/errors.py
hubitat_maker_api_client/event_socket.py
hubitat_maker_api_client-2.6.0.dist-info/LICENSE
hubitat_maker_api_client-2.6.0.dist-info/METADATA
hubitat_maker_api_client-2.6.0.dist-info/WHEEL
hubitat_maker_api_client-2.6.0.dist-info/RECORD
