Metadata-Version: 2.3
Name: hubitat-maker-api-client
Version: 2.6.0
Summary: Control Hubitat Maker API
Author: Jimming Cheng
Author-email: jimming@gmail.com
Requires-Python: >=3.11,<4.0
Classifier: Programming Language :: Python :: 3
Classifier: Programming Language :: Python :: 3.11
Classifier: Programming Language :: Python :: 3.12
Classifier: Programming Language :: Python :: 3.13
Requires-Dist: requests (>=2.31.0,<3.0.0)
